{
	"info": {
		"name": "Korean OCR Data Set",
		"description": "Korean OCR Data Set (word handwrite)",
		"date_created": "2021-01-31 14:08:14"
	},
	"image": {
		"file_name": "12340083040.jpg",
		"width": 484,
		"height": 108,
		"dpi": 300,
		"bit": 24
	},
	"text": {
		"type": "word",
		"output": "handwrite",
		"word": [
			{
				"charbox": [
					55,
					12,
					111,
					92
				],
				"value": "연"
			},
			{
				"charbox": [
					136,
					25,
					210,
					104
				],
				"value": "습"
			},
			{
				"charbox": [
					254,
					21,
					318,
					95
				],
				"value": "하"
			},
			{
				"charbox": [
					333,
					30,
					422,
					95
				],
				"value": "다"
			}
		]
	},
	"license": {
		"output": "handwrite",
		"font": "",
		"font_no": "",
		"font_license": "",
		"font_url": "",
		"writer_no": "123",
		"writer_gender": "female",
		"writer_age": "50"
	}
}