{
	"info": {
		"name": "Korean OCR Data Set",
		"description": "Korean OCR Data Set (word handwrite)",
		"date_created": "2021-01-31 14:06:37"
	},
	"image": {
		"file_name": "12340080025.jpg",
		"width": 482,
		"height": 107,
		"dpi": 300,
		"bit": 24
	},
	"text": {
		"type": "word",
		"output": "handwrite",
		"word": [
			{
				"charbox": [
					45,
					8,
					93,
					91
				],
				"value": "소"
			},
			{
				"charbox": [
					149,
					9,
					220,
					93
				],
				"value": "리"
			},
			{
				"charbox": [
					280,
					10,
					339,
					83
				],
				"value": "치"
			},
			{
				"charbox": [
					376,
					1,
					438,
					64
				],
				"value": "다"
			}
		]
	},
	"license": {
		"output": "handwrite",
		"font": "",
		"font_no": "",
		"font_license": "",
		"font_url": "",
		"writer_no": "123",
		"writer_gender": "female",
		"writer_age": "50"
	}
}