{
	"info": {
		"name": "Korean OCR Data Set",
		"description": "Korean OCR Data Set (word handwrite)",
		"date_created": "2021-01-31 13:41:23"
	},
	"image": {
		"file_name": "12340043002.jpg",
		"width": 340,
		"height": 110,
		"dpi": 300,
		"bit": 24
	},
	"text": {
		"type": "word",
		"output": "handwrite",
		"word": [
			{
				"charbox": [
					41,
					26,
					93,
					79
				],
				"value": "그"
			},
			{
				"charbox": [
					133,
					17,
					206,
					91
				],
				"value": "렇"
			},
			{
				"charbox": [
					231,
					23,
					300,
					79
				],
				"value": "다"
			}
		]
	},
	"license": {
		"output": "handwrite",
		"font": "",
		"font_no": "",
		"font_license": "",
		"font_url": "",
		"writer_no": "123",
		"writer_gender": "female",
		"writer_age": "50"
	}
}