{
	"info": {
		"name": "Korean OCR Data Set",
		"description": "Korean OCR Data Set (word handwrite)",
		"date_created": "2021-01-31 13:19:36"
	},
	"image": {
		"file_name": "12340012051.jpg",
		"width": 228,
		"height": 110,
		"dpi": 300,
		"bit": 24
	},
	"text": {
		"type": "word",
		"output": "handwrite",
		"word": [
			{
				"charbox": [
					32,
					10,
					84,
					84
				],
				"value": "무"
			},
			{
				"charbox": [
					135,
					11,
					172,
					78
				],
				"value": "료"
			}
		]
	},
	"license": {
		"output": "handwrite",
		"font": "",
		"font_no": "",
		"font_license": "",
		"font_url": "",
		"writer_no": "123",
		"writer_gender": "female",
		"writer_age": "50"
	}
}