{
	"info": {
		"name": "Korean OCR Data Set",
		"description": "Korean OCR Data Set (word handwrite)",
		"date_created": "2021-01-31 13:21:23"
	},
	"image": {
		"file_name": "12340016049.jpg",
		"width": 230,
		"height": 108,
		"dpi": 300,
		"bit": 24
	},
	"text": {
		"type": "word",
		"output": "handwrite",
		"word": [
			{
				"charbox": [
					25,
					12,
					96,
					101
				],
				"value": "뽑"
			},
			{
				"charbox": [
					141,
					27,
					203,
					82
				],
				"value": "다"
			}
		]
	},
	"license": {
		"output": "handwrite",
		"font": "",
		"font_no": "",
		"font_license": "",
		"font_url": "",
		"writer_no": "123",
		"writer_gender": "female",
		"writer_age": "50"
	}
}