{
	"info": {
		"name": "Korean OCR Data Set",
		"description": "Korean OCR Data Set (word handwrite)",
		"date_created": "2021-01-31 15:38:40"
	},
	"image": {
		"file_name": "12440095023.jpg",
		"width": 590,
		"height": 109,
		"dpi": 300,
		"bit": 24
	},
	"text": {
		"type": "word",
		"output": "handwrite",
		"word": [
			{
				"charbox": [
					46,
					15,
					122,
					109
				],
				"value": "되"
			},
			{
				"charbox": [
					149,
					7,
					212,
					86
				],
				"value": "돌"
			},
			{
				"charbox": [
					242,
					7,
					335,
					80
				],
				"value": "아"
			},
			{
				"charbox": [
					354,
					17,
					415,
					89
				],
				"value": "보"
			},
			{
				"charbox": [
					421,
					13,
					515,
					87
				],
				"value": "다"
			}
		]
	},
	"license": {
		"output": "handwrite",
		"font": "",
		"font_no": "",
		"font_license": "",
		"font_url": "",
		"writer_no": "124",
		"writer_gender": "female",
		"writer_age": "50"
	}
}