{
	"info": {
		"name": "Korean OCR Data Set",
		"description": "Korean OCR Data Set (word handwrite)",
		"date_created": "2021-01-31 14:46:38"
	},
	"image": {
		"file_name": "12440025040.jpg",
		"width": 229,
		"height": 110,
		"dpi": 300,
		"bit": 24
	},
	"text": {
		"type": "word",
		"output": "handwrite",
		"word": [
			{
				"charbox": [
					40,
					12,
					112,
					98
				],
				"value": "우"
			},
			{
				"charbox": [
					137,
					17,
					204,
					87
				],
				"value": "려"
			}
		]
	},
	"license": {
		"output": "handwrite",
		"font": "",
		"font_no": "",
		"font_license": "",
		"font_url": "",
		"writer_no": "124",
		"writer_gender": "female",
		"writer_age": "50"
	}
}