{
	"info": {
		"name": "Korean OCR Data Set",
		"description": "Korean OCR Data Set (word handwrite)",
		"date_created": "2021-01-31 14:23:32"
	},
	"image": {
		"file_name": "12440007007.jpg",
		"width": 233,
		"height": 110,
		"dpi": 300,
		"bit": 24
	},
	"text": {
		"type": "word",
		"output": "handwrite",
		"word": [
			{
				"charbox": [
					18,
					18,
					95,
					97
				],
				"value": "나"
			},
			{
				"charbox": [
					124,
					10,
					184,
					88
				],
				"value": "비"
			}
		]
	},
	"license": {
		"output": "handwrite",
		"font": "",
		"font_no": "",
		"font_license": "",
		"font_url": "",
		"writer_no": "124",
		"writer_gender": "female",
		"writer_age": "50"
	}
}