{
	"info": {
		"name": "Korean OCR Data Set",
		"description": "Korean OCR Data Set (word handwrite)",
		"date_created": "2021-01-31 15:07:09"
	},
	"image": {
		"file_name": "12440048009.jpg",
		"width": 340,
		"height": 110,
		"dpi": 300,
		"bit": 24
	},
	"text": {
		"type": "word",
		"output": "handwrite",
		"word": [
			{
				"charbox": [
					31,
					23,
					104,
					101
				],
				"value": "러"
			},
			{
				"charbox": [
					126,
					25,
					182,
					96
				],
				"value": "시"
			},
			{
				"charbox": [
					209,
					22,
					274,
					84
				],
				"value": "아"
			}
		]
	},
	"license": {
		"output": "handwrite",
		"font": "",
		"font_no": "",
		"font_license": "",
		"font_url": "",
		"writer_no": "124",
		"writer_gender": "female",
		"writer_age": "50"
	}
}