{
	"info": {
		"name": "Korean OCR Data Set",
		"description": "Korean OCR Data Set (word handwrite)",
		"date_created": "2021-01-31 15:01:51"
	},
	"image": {
		"file_name": "12440041013.jpg",
		"width": 342,
		"height": 109,
		"dpi": 300,
		"bit": 24
	},
	"text": {
		"type": "word",
		"output": "handwrite",
		"word": [
			{
				"charbox": [
					44,
					5,
					103,
					85
				],
				"value": "겁"
			},
			{
				"charbox": [
					152,
					14,
					205,
					77
				],
				"value": "나"
			},
			{
				"charbox": [
					233,
					8,
					302,
					77
				],
				"value": "다"
			}
		]
	},
	"license": {
		"output": "handwrite",
		"font": "",
		"font_no": "",
		"font_license": "",
		"font_url": "",
		"writer_no": "124",
		"writer_gender": "female",
		"writer_age": "50"
	}
}