{
	"info": {
		"name": "Korean OCR Data Set",
		"description": "Korean OCR Data Set (word handwrite)",
		"date_created": "2021-01-31 15:03:51"
	},
	"image": {
		"file_name": "12440043036.jpg",
		"width": 342,
		"height": 108,
		"dpi": 300,
		"bit": 24
	},
	"text": {
		"type": "word",
		"output": "handwrite",
		"word": [
			{
				"charbox": [
					36,
					9,
					93,
					108
				],
				"value": "기"
			},
			{
				"charbox": [
					140,
					22,
					209,
					102
				],
				"value": "숙"
			},
			{
				"charbox": [
					227,
					18,
					292,
					89
				],
				"value": "사"
			}
		]
	},
	"license": {
		"output": "handwrite",
		"font": "",
		"font_no": "",
		"font_license": "",
		"font_url": "",
		"writer_no": "124",
		"writer_gender": "female",
		"writer_age": "50"
	}
}