{
	"info": {
		"name": "Korean OCR Data Set",
		"description": "Korean OCR Data Set (word handwrite)",
		"date_created": "2021-01-31 15:20:04"
	},
	"image": {
		"file_name": "12440063045.jpg",
		"width": 342,
		"height": 108,
		"dpi": 300,
		"bit": 24
	},
	"text": {
		"type": "word",
		"output": "handwrite",
		"word": [
			{
				"charbox": [
					33,
					16,
					99,
					104
				],
				"value": "철"
			},
			{
				"charbox": [
					138,
					34,
					201,
					94
				],
				"value": "저"
			},
			{
				"charbox": [
					230,
					15,
					287,
					101
				],
				"value": "히"
			}
		]
	},
	"license": {
		"output": "handwrite",
		"font": "",
		"font_no": "",
		"font_license": "",
		"font_url": "",
		"writer_no": "124",
		"writer_gender": "female",
		"writer_age": "50"
	}
}