{
	"info": {
		"name": "Korean OCR Data Set",
		"description": "Korean OCR Data Set (word handwrite)",
		"date_created": "2021-01-31 15:04:15"
	},
	"image": {
		"file_name": "12440044019.jpg",
		"width": 343,
		"height": 111,
		"dpi": 300,
		"bit": 24
	},
	"text": {
		"type": "word",
		"output": "handwrite",
		"word": [
			{
				"charbox": [
					48,
					14,
					99,
					93
				],
				"value": "끝"
			},
			{
				"charbox": [
					135,
					21,
					199,
					99
				],
				"value": "없"
			},
			{
				"charbox": [
					211,
					28,
					285,
					82
				],
				"value": "다"
			}
		]
	},
	"license": {
		"output": "handwrite",
		"font": "",
		"font_no": "",
		"font_license": "",
		"font_url": "",
		"writer_no": "124",
		"writer_gender": "female",
		"writer_age": "50"
	}
}