{
	"info": {
		"name": "Korean OCR Data Set",
		"description": "Korean OCR Data Set (word handwrite)",
		"date_created": "2021-01-31 15:05:34"
	},
	"image": {
		"file_name": "12440046014.jpg",
		"width": 344,
		"height": 109,
		"dpi": 300,
		"bit": 24
	},
	"text": {
		"type": "word",
		"output": "handwrite",
		"word": [
			{
				"charbox": [
					35,
					24,
					117,
					88
				],
				"value": "대"
			},
			{
				"charbox": [
					128,
					18,
					197,
					94
				],
				"value": "부"
			},
			{
				"charbox": [
					202,
					18,
					270,
					93
				],
				"value": "분"
			}
		]
	},
	"license": {
		"output": "handwrite",
		"font": "",
		"font_no": "",
		"font_license": "",
		"font_url": "",
		"writer_no": "124",
		"writer_gender": "female",
		"writer_age": "50"
	}
}