{
	"info": {
		"name": "Korean OCR Data Set",
		"description": "Korean OCR Data Set (word handwrite)",
		"date_created": "2021-01-31 15:34:19"
	},
	"image": {
		"file_name": "12440086023.jpg",
		"width": 482,
		"height": 108,
		"dpi": 300,
		"bit": 24
	},
	"text": {
		"type": "word",
		"output": "handwrite",
		"word": [
			{
				"charbox": [
					60,
					7,
					126,
					85
				],
				"value": "인"
			},
			{
				"charbox": [
					161,
					13,
					227,
					89
				],
				"value": "천"
			},
			{
				"charbox": [
					254,
					28,
					304,
					102
				],
				"value": "공"
			},
			{
				"charbox": [
					336,
					14,
					416,
					101
				],
				"value": "항"
			}
		]
	},
	"license": {
		"output": "handwrite",
		"font": "",
		"font_no": "",
		"font_license": "",
		"font_url": "",
		"writer_no": "124",
		"writer_gender": "female",
		"writer_age": "50"
	}
}