{
	"info": {
		"name": "Korean OCR Data Set",
		"description": "Korean OCR Data Set (word handwrite)",
		"date_created": "2021-01-31 14:19:31"
	},
	"image": {
		"file_name": "12440005012.jpg",
		"width": 229,
		"height": 110,
		"dpi": 300,
		"bit": 24
	},
	"text": {
		"type": "word",
		"output": "handwrite",
		"word": [
			{
				"charbox": [
					16,
					19,
					91,
					91
				],
				"value": "규"
			},
			{
				"charbox": [
					117,
					20,
					177,
					97
				],
				"value": "정"
			}
		]
	},
	"license": {
		"output": "handwrite",
		"font": "",
		"font_no": "",
		"font_license": "",
		"font_url": "",
		"writer_no": "124",
		"writer_gender": "female",
		"writer_age": "50"
	}
}