{
	"info": {
		"name": "Korean OCR Data Set",
		"description": "Korean OCR Data Set (word handwrite)",
		"date_created": "2021-01-31 14:26:29"
	},
	"image": {
		"file_name": "12440008042.jpg",
		"width": 231,
		"height": 108,
		"dpi": 300,
		"bit": 24
	},
	"text": {
		"type": "word",
		"output": "handwrite",
		"word": [
			{
				"charbox": [
					0,
					14,
					95,
					74
				],
				"value": "다"
			},
			{
				"charbox": [
					103,
					4,
					172,
					75
				],
				"value": "만"
			}
		]
	},
	"license": {
		"output": "handwrite",
		"font": "",
		"font_no": "",
		"font_license": "",
		"font_url": "",
		"writer_no": "124",
		"writer_gender": "female",
		"writer_age": "50"
	}
}